setup.py
dsnd_probability_exercise/Binomialdistribution.py
dsnd_probability_exercise/Gaussiandistribution.py
dsnd_probability_exercise/Generaldistribution.py
dsnd_probability_exercise/__init__.py
dsnd_probability_exercise.egg-info/PKG-INFO
dsnd_probability_exercise.egg-info/SOURCES.txt
dsnd_probability_exercise.egg-info/dependency_links.txt
dsnd_probability_exercise.egg-info/not-zip-safe
dsnd_probability_exercise.egg-info/top_level.txt