Metadata-Version: 1.0
Name: dsnd-probability-exercise
Version: 0.1
Summary: Gaussian and Binomial distributions
Home-page: UNKNOWN
Author: Jennifer Hui
Author-email: jenniferm.hui@gmail.com
License: UNKNOWN
Platform: UNKNOWN
